<?xml version="1.0" encoding="utf-8" ?>
<Defs>

    <ThingDef ParentName="BuildingBase">
        <defName>FabricationExpositor</defName>
        <label>fabrication expositor</label>
        <description>This expositor enables the construction of advanced security assemblies. The eternal flame core enclosed within the containment field is a source of great power and knowledge.\n\nKeep it safe. Keep it contained!</description>
        <graphicData>
            <texPath>Things/Building/Misc/Fabrication_Expositor</texPath>
            <graphicClass>Graphic_Single</graphicClass>
            <drawSize>3</drawSize>
            <drawOffset>(0,0,0.7)</drawOffset>
        </graphicData>
        <uiIconScale>0.85</uiIconScale>
        <researchPrerequisites><li>FabricationExpositor</li></researchPrerequisites>
        <!-- Make our own research for this to unlock the new security buildings. -->
        <size>(2,2)</size>
        <rotatable>false</rotatable>
        <altitudeLayer>Building</altitudeLayer>
        <passability>PassThroughOnly</passability>
        <castEdgeShadows>true</castEdgeShadows>
        <fillPercent>0.5</fillPercent>
        <designationHotKey>Misc4</designationHotKey>
        <designationCategory>Misc</designationCategory>
        <minifiedDef>MinifiedThing</minifiedDef>
        <canOverlapZones>false</canOverlapZones>
        <terrainAffordanceNeeded>Medium</terrainAffordanceNeeded>
        <thingCategories>
            <li>BuildingsMisc</li>
        </thingCategories>
        <statBases>
            <MaxHitPoints>350</MaxHitPoints>
            <WorkToBuild>10000</WorkToBuild>
            <Mass>50</Mass>
            <Flammability>1.0</Flammability>
        </statBases>
        <costList>
            <Steel>40</Steel>
            <Plasteel>50</Plasteel>
            <Gold>20</Gold>
            <ComponentIndustrial>8</ComponentIndustrial>
            <Bast_Eternal_Flame_Core>1</Bast_Eternal_Flame_Core>
        </costList>
        <building>
            <destroySound>BuildingDestroyed_Metal_Medium</destroySound>
        </building>
        <comps>
            <li Class="CompProperties_Power">
                <compClass>CompPowerTrader</compClass>
                <shortCircuitInRain>true</shortCircuitInRain>
                <basePowerConsumption>200</basePowerConsumption>
            </li>
            <li Class="CompProperties_Glower">
                <glowRadius>6</glowRadius>
                <glowColor>(0,171,214,0)</glowColor>
            </li>
            <li Class="CompProperties_Breakdownable"/>
            <li Class="CompProperties_Flickable"/>
            <li Class="CompProperties_Facility">
                <statOffsets>
                    <WorkTableWorkSpeedFactor>0.1</WorkTableWorkSpeedFactor>
                </statOffsets>
                <maxSimultaneous>1</maxSimultaneous>
            </li>
        </comps>
        <placeWorkers>
            <li>PlaceWorker_ShowFacilitiesConnections</li>
        </placeWorkers>
        <constructionSkillPrerequisite>9</constructionSkillPrerequisite>
    </ThingDef>

</Defs>